setup.py
henrio/__init__.py
henrio/bases.py
henrio/futures.py
henrio/io.py
henrio/locks.py
henrio/loop.py
henrio/protocols.py
henrio/queue.py
henrio/selector.py
henrio/timeout.py
henrio/universals.py
henrio/windows.py
henrio/workers.py
henrio/yields.py
henrio.egg-info/PKG-INFO
henrio.egg-info/SOURCES.txt
henrio.egg-info/dependency_links.txt
henrio.egg-info/top_level.txt