Metadata-Version: 1.0
Name: henrio
Version: 3.4
Summary: My trials screwing with async loops
Home-page: https://github.com/henry232323/henrio
Author: henry232323
Author-email: henry@typheus.me
License: GPL
Platform: UNKNOWN
